{"nm":"Star","ddd":0,"h":250,"w":251,"meta":{"g":"@lottiefiles/toolkit-js 0.33.2"},"layers":[{"ty":4,"nm":"Stroke 30","sr":1,"st":0,"op":51,"ip":0,"hd":false,"ddd":0,"bm":0,"hasMask":false,"ao":0,"ks":{"a":{"a":0,"k":[0,0,0],"ix":1},"s":{"a":0,"k":[100,100,100],"ix":6},"sk":{"a":0,"k":0},"p":{"a":0,"k":[-11.841,-2.525,0],"ix":2},"r":{"a":0,"k":0,"ix":10},"sa":{"a":0,"k":0},"o":{"a":0,"k":100,"ix":11}},"ef":[],"shapes":[{"ty":"gr","bm":0,"hd":false,"mn":"ADBE Vector Group","nm":"Stroke 30","ix":1,"cix":2,"np":2,"it":[{"ty":"sh","bm":0,"hd":false,"mn":"ADBE Vector Shape - Group","nm":"Path 1","ix":1,"d":1,"ks":{"a":0,"k":{"c":false,"i":[[3.264,-0.275],[-1.1460000000000001,-3.955],[-3.406,0.835]],"o":[[1.4239999999999997,-2.755],[-3.8160000000000003,-1.9749999999999999],[-1.566,3.315]],"v":[[3.264,-0.275],[-2.486,-2.965],[-1.566,3.315]]},"ix":2},"_render":true},{"ty":"st","bm":0,"hd":false,"mn":"ADBE Vector Graphic - Stroke","nm":"Stroke 1","lc":2,"lj":2,"ml":1,"o":{"a":0,"k":100,"ix":4},"w":{"a":0,"k":3,"ix":5},"c":{"a":0,"k":[0.1333,0.7216,0.8118,1],"ix":3},"_render":true},{"ty":"tr","a":{"a":0,"k":[0,0],"ix":1},"s":{"a":0,"k":[100,100],"ix":3},"sk":{"a":0,"k":0,"ix":4},"p":{"a":0,"k":[0,0],"ix":2},"r":{"a":0,"k":0,"ix":6},"sa":{"a":0,"k":0,"ix":5},"o":{"a":0,"k":100,"ix":7},"_render":true}],"_render":true}],"ind":1,"parent":3,"completed":true},{"ty":4,"nm":"Stroke 26","sr":1,"st":0,"op":51,"ip":0,"hd":false,"ddd":0,"bm":0,"hasMask":false,"ao":0,"ks":{"a":{"a":0,"k":[0,0,0],"ix":1},"s":{"a":0,"k":[100,100,100],"ix":6},"sk":{"a":0,"k":0},"p":{"a":0,"k":[0.903,-12.241,0],"ix":2},"r":{"a":0,"k":0,"ix":10},"sa":{"a":0,"k":0},"o":{"a":0,"k":100,"ix":11}},"ef":[],"shapes":[{"ty":"gr","bm":0,"hd":false,"mn":"ADBE Vector Group","nm":"Stroke 26","ix":1,"cix":2,"np":2,"it":[{"ty":"sh","bm":0,"hd":false,"mn":"ADBE Vector Shape - Group","nm":"Path 1","ix":1,"d":1,"ks":{"a":0,"k":{"c":false,"i":[[3.264,-0.275],[-1.1460000000000001,-3.955],[-3.406,0.835]],"o":[[1.4239999999999997,-2.755],[-3.8160000000000003,-1.9749999999999999],[-1.566,3.315]],"v":[[3.264,-0.275],[-2.486,-2.965],[-1.566,3.315]]},"ix":2},"_render":true},{"ty":"st","bm":0,"hd":false,"mn":"ADBE Vector Graphic - Stroke","nm":"Stroke 1","lc":2,"lj":2,"ml":1,"o":{"a":0,"k":100,"ix":4},"w":{"a":0,"k":3,"ix":5},"c":{"a":0,"k":[0.1333,0.7216,0.8118,1],"ix":3},"_render":true},{"ty":"tr","a":{"a":0,"k":[0,0],"ix":1},"s":{"a":0,"k":[100,100],"ix":3},"sk":{"a":0,"k":0,"ix":4},"p":{"a":0,"k":[0,0],"ix":2},"r":{"a":0,"k":0,"ix":6},"sa":{"a":0,"k":0,"ix":5},"o":{"a":0,"k":100,"ix":7},"_render":true}],"_render":true}],"ind":2,"parent":3,"completed":true},{"ty":4,"nm":"Stroke 34","sr":1,"st":0,"op":51,"ip":0,"hd":false,"ddd":0,"bm":0,"hasMask":false,"ao":0,"ks":{"a":{"a":0,"k":[0,0,0],"ix":1},"s":{"a":0,"k":[100,100,100],"ix":6},"sk":{"a":0,"k":0},"p":{"a":1,"k":[{"o":{"x":0.45,"y":0},"i":{"x":0.3,"y":1},"s":[1.361,-2.395,0],"t":0,"ti":null,"to":null},{"o":{"x":0.45,"y":0},"i":{"x":0.3,"y":1},"s":[0.133,-2.63,0],"t":12,"ti":null,"to":null},{"o":{"x":0.45,"y":0},"i":{"x":0.3,"y":1},"s":[-1.515,-0.304,0],"t":24,"ti":null,"to":null},{"o":{"x":0.45,"y":0},"i":{"x":0.3,"y":1},"s":[0.133,-2.63,0],"t":36,"ti":null,"to":null},{"s":[1.361,-2.395,0],"t":48}],"ix":2},"r":{"a":0,"k":0,"ix":10},"sa":{"a":0,"k":0},"o":{"a":0,"k":100,"ix":11}},"ef":[],"shapes":[{"ty":"gr","bm":0,"hd":false,"mn":"ADBE Vector Group","nm":"Stroke 34","ix":1,"cix":2,"np":2,"it":[{"ty":"sh","bm":0,"hd":false,"mn":"ADBE Vector Shape - Group","nm":"Path 1","ix":1,"d":1,"ks":{"a":1,"k":[{"o":{"x":0.45,"y":0},"i":{"x":0.3,"y":1},"s":[{"c":true,"i":[[-9.795,4.715],[0.14499999999999957,9.775],[11.275,-4.0649999999999995]],"o":[[-6.505,9.145],[9.955,2.475],[7.985,-8.495]],"v":[[-9.795,4.715],[5.055,6.125],[7.985,-8.495]]}],"t":0},{"o":{"x":0.45,"y":0},"i":{"x":0.3,"y":1},"s":[{"c":true,"i":[[-6.618,2.496],[-2.692,5.657],[5.844,-4.338]],"o":[[-4.439,5.216],[7.118,-1.6429999999999998],[4.477,-6.095]],"v":[[-6.618,2.496],[2.218,2.007],[4.477,-6.095]]}],"t":12},{"o":{"x":0.45,"y":0},"i":{"x":0.3,"y":1},"s":[{"c":true,"i":[[-9.795,4.715],[0.14499999999999957,9.775],[11.275,-4.0649999999999995]],"o":[[-6.505,9.145],[9.955,2.475],[7.985,-8.495]],"v":[[-9.795,4.715],[5.055,6.125],[7.985,-8.495]]}],"t":24},{"o":{"x":0.45,"y":0},"i":{"x":0.3,"y":1},"s":[{"c":true,"i":[[-6.618,2.496],[-2.692,5.657],[5.844,-4.338]],"o":[[-4.439,5.216],[7.118,-1.6429999999999998],[4.477,-6.095]],"v":[[-6.618,2.496],[2.218,2.007],[4.477,-6.095]]}],"t":36},{"s":[{"c":true,"i":[[-9.795,4.715],[0.14499999999999957,9.775],[11.275,-4.0649999999999995]],"o":[[-6.505,9.145],[9.955,2.475],[7.985,-8.495]],"v":[[-9.795,4.715],[5.055,6.125],[7.985,-8.495]]}],"t":48}],"ix":2},"_render":true},{"ty":"st","bm":0,"hd":false,"mn":"ADBE Vector Graphic - Stroke","nm":"Stroke 1","lc":2,"lj":2,"ml":1,"o":{"a":0,"k":100,"ix":4},"w":{"a":0,"k":3,"ix":5},"c":{"a":0,"k":[0.1333,0.7216,0.8118,1],"ix":3},"_render":true},{"ty":"tr","a":{"a":0,"k":[0,0],"ix":1},"s":{"a":0,"k":[100,100],"ix":3},"sk":{"a":0,"k":0,"ix":4},"p":{"a":0,"k":[0,0],"ix":2},"r":{"a":0,"k":0,"ix":6},"sa":{"a":0,"k":0,"ix":5},"o":{"a":0,"k":100,"ix":7},"_render":true}],"_render":true}],"ind":3,"parent":4,"completed":true},{"ty":4,"nm":"Stroke 22","sr":1,"st":0,"op":51,"ip":0,"hd":false,"ddd":0,"bm":0,"hasMask":false,"ao":0,"ks":{"a":{"a":0,"k":[10.5,8.5,0],"ix":1},"s":{"a":0,"k":[100,100,100],"ix":6},"sk":{"a":0,"k":0},"p":{"a":1,"k":[{"o":{"x":0.888,"y":0},"i":{"x":0.711,"y":1},"s":[73.619,176.719,0],"t":0,"ti":[-16.119,-26.219,0],"to":[0,0,0]},{"o":{"x":0.273,"y":0},"i":{"x":0.135,"y":1},"s":[129.619,193.219,0],"t":12,"ti":[0,0,0],"to":[18.869,-23.531,0]},{"o":{"x":0.888,"y":0},"i":{"x":0.711,"y":1},"s":[173.541,174.208,0],"t":24,"ti":[16.131,-22.469,0],"to":[0,0,0]},{"o":{"x":0.273,"y":0},"i":{"x":0.135,"y":1},"s":[129.869,193.219,0],"t":36,"ti":[0,0,0],"to":[-15.131,-25.781,0]},{"s":[73.619,176.719,0],"t":48}],"ix":2},"r":{"a":1,"k":[{"o":{"x":0.888,"y":0},"i":{"x":0.711,"y":1},"s":[0],"t":0},{"o":{"x":0.273,"y":0},"i":{"x":0.135,"y":1},"s":[42.294],"t":12},{"o":{"x":0.888,"y":0},"i":{"x":0.711,"y":1},"s":[75.154],"t":24},{"o":{"x":0.273,"y":0},"i":{"x":0.135,"y":1},"s":[29.579],"t":36},{"s":[0],"t":48}],"ix":10},"sa":{"a":0,"k":0},"o":{"a":0,"k":100,"ix":11}},"ef":[],"shapes":[{"ty":"gr","bm":0,"hd":false,"mn":"ADBE Vector Group","nm":"Stroke 22","ix":1,"cix":2,"np":3,"it":[{"ty":"sh","bm":0,"hd":false,"mn":"ADBE Vector Shape - Group","nm":"Path 1","ix":1,"d":1,"ks":{"a":1,"k":[{"o":{"x":0.888,"y":0},"i":{"x":0.711,"y":1},"s":[{"c":true,"i":[[-2.525,-23.908],[-18.015,-33.818],[-21.395,-8.748],[-34.555,3.702],[-13.195,14.542],[-4.935,31.362000000000002],[12.785,12.902],[30.015,12.632],[20.035,-11.108],[22.974999999999998,-27.068]],"o":[[-2.525,-23.908],[-27.285,-25.428],[-21.395,-8.748],[-29.255000000000003,12.712],[-13.195,14.542],[4.595,31.912000000000003],[12.785,12.902],[34.095,0.5419999999999998],[20.035,-11.108],[13.355,-34.598]],"v":[[-2.525,-23.908],[-22.645,-29.628],[-21.395,-8.748],[-31.905,8.212],[-13.195,14.542],[-0.165,31.632],[12.785,12.902],[32.055,6.582],[20.035,-11.108],[18.165,-30.838]]}],"t":0},{"o":{"x":0.273,"y":0},"i":{"x":0.135,"y":1},"s":[{"c":true,"i":[[-1.614,-24.085],[-15.485,-31.05],[-20.472,-9.591],[-27.096999999999998,5.665000000000001],[-6.021,12.259],[2.215,25.204],[11.179,9.77],[22.738999999999997,13.518],[16.7,-5.962],[23.087999999999997,-21.387]],"o":[[-1.614,-24.085],[-24.755,-22.66],[-20.472,-9.591],[-21.797,14.675],[-6.021,12.259],[10.033999999999999,22.015],[11.179,9.77],[25.61,3.997],[16.7,-5.962],[13.468,-28.917]],"v":[[-1.614,-24.085],[-20.115,-26.86],[-20.472,-9.591],[-24.447,10.175],[-6.021,12.259],[6.928,23.282],[11.179,9.77],[24.176,8.754],[16.7,-5.962],[18.278,-25.157]]}],"t":12},{"o":{"x":0.888,"y":0},"i":{"x":0.711,"y":1},"s":[{"c":true,"i":[[-2.525,-23.908],[-18.015,-33.818],[-21.395,-8.748],[-34.555,3.702],[-13.195,14.542],[-4.935,31.362000000000002],[12.785,12.902],[30.015,12.632],[20.035,-11.108],[22.974999999999998,-27.068]],"o":[[-2.525,-23.908],[-27.285,-25.428],[-21.395,-8.748],[-29.255000000000003,12.712],[-13.195,14.542],[4.595,31.912000000000003],[12.785,12.902],[34.095,0.5419999999999998],[20.035,-11.108],[13.355,-34.598]],"v":[[-2.525,-23.908],[-22.645,-29.628],[-21.395,-8.748],[-31.905,8.212],[-13.195,14.542],[-0.165,31.632],[12.785,12.902],[32.055,6.582],[20.035,-11.108],[18.165,-30.838]]}],"t":24},{"o":{"x":0.273,"y":0},"i":{"x":0.135,"y":1},"s":[{"c":true,"i":[[-1.614,-24.085],[-15.485,-31.05],[-20.472,-9.591],[-27.096999999999998,5.665000000000001],[-6.021,12.259],[2.215,25.204],[11.179,9.77],[22.738999999999997,13.518],[16.7,-5.962],[23.087999999999997,-21.387]],"o":[[-1.614,-24.085],[-24.755,-22.66],[-20.472,-9.591],[-21.797,14.675],[-6.021,12.259],[10.033999999999999,22.015],[11.179,9.77],[25.61,3.997],[16.7,-5.962],[13.468,-28.917]],"v":[[-1.614,-24.085],[-20.115,-26.86],[-20.472,-9.591],[-24.447,10.175],[-6.021,12.259],[6.928,23.282],[11.179,9.77],[24.176,8.754],[16.7,-5.962],[18.278,-25.157]]}],"t":36},{"s":[{"c":true,"i":[[-2.525,-23.908],[-18.015,-33.818],[-21.395,-8.748],[-34.555,3.702],[-13.195,14.542],[-4.935,31.362000000000002],[12.785,12.902],[30.015,12.632],[20.035,-11.108],[22.974999999999998,-27.068]],"o":[[-2.525,-23.908],[-27.285,-25.428],[-21.395,-8.748],[-29.255000000000003,12.712],[-13.195,14.542],[4.595,31.912000000000003],[12.785,12.902],[34.095,0.5419999999999998],[20.035,-11.108],[13.355,-34.598]],"v":[[-2.525,-23.908],[-22.645,-29.628],[-21.395,-8.748],[-31.905,8.212],[-13.195,14.542],[-0.165,31.632],[12.785,12.902],[32.055,6.582],[20.035,-11.108],[18.165,-30.838]]}],"t":48}],"ix":2},"_render":true},{"ty":"st","bm":0,"hd":false,"mn":"ADBE Vector Graphic - Stroke","nm":"Stroke 1","lc":2,"lj":2,"ml":1,"o":{"a":0,"k":100,"ix":4},"w":{"a":0,"k":3,"ix":5},"c":{"a":0,"k":[0.1333,0.7216,0.8118,1],"ix":3},"_render":true},{"ty":"fl","bm":0,"hd":false,"mn":"ADBE Vector Graphic - Fill","nm":"Fill 1","c":{"a":0,"k":[0.4,0.851,0.9098,1],"ix":4},"r":1,"o":{"a":0,"k":100,"ix":5},"_render":true},{"ty":"tr","a":{"a":0,"k":[0,0],"ix":1},"s":{"a":0,"k":[100,100],"ix":3},"sk":{"a":0,"k":0,"ix":4},"p":{"a":0,"k":[0,0],"ix":2},"r":{"a":0,"k":0,"ix":6},"sa":{"a":0,"k":0,"ix":5},"o":{"a":0,"k":100,"ix":7},"_render":true}],"_render":true}],"ind":4,"completed":true},{"ty":4,"nm":"Stroke 14","sr":1,"st":0,"op":51,"ip":0,"hd":false,"ddd":0,"bm":0,"hasMask":false,"ao":0,"ks":{"a":{"a":0,"k":[0,0,0],"ix":1},"s":{"a":0,"k":[100,100,100],"ix":6},"sk":{"a":0,"k":0},"p":{"a":0,"k":[-5.753,-18.931,0],"ix":2},"r":{"a":0,"k":0,"ix":10},"sa":{"a":0,"k":0},"o":{"a":0,"k":100,"ix":11}},"ef":[],"shapes":[{"ty":"gr","bm":0,"hd":false,"mn":"ADBE Vector Group","nm":"Stroke 14","ix":1,"cix":2,"np":2,"it":[{"ty":"sh","bm":0,"hd":false,"mn":"ADBE Vector Shape - Group","nm":"Path 1","ix":1,"d":1,"ks":{"a":0,"k":{"c":false,"i":[[3.03,4.735],[5.15,-3.3050000000000006],[-2.5,-3.3150000000000004]],"o":[[5.15,0.8050000000000002],[0.9300000000000002,-5.575],[-4.62,0.615]],"v":[[3.03,4.735],[3.04,-4.445],[-4.62,0.615]]},"ix":2},"_render":true},{"ty":"st","bm":0,"hd":false,"mn":"ADBE Vector Graphic - Stroke","nm":"Stroke 1","lc":2,"lj":2,"ml":1,"o":{"a":0,"k":100,"ix":4},"w":{"a":0,"k":3,"ix":5},"c":{"a":0,"k":[0.1333,0.7216,0.8118,1],"ix":3},"_render":true},{"ty":"tr","a":{"a":0,"k":[0,0],"ix":1},"s":{"a":0,"k":[100,100],"ix":3},"sk":{"a":0,"k":0,"ix":4},"p":{"a":0,"k":[0,0],"ix":2},"r":{"a":0,"k":0,"ix":6},"sa":{"a":0,"k":0,"ix":5},"o":{"a":0,"k":100,"ix":7},"_render":true}],"_render":true}],"ind":5,"parent":7,"completed":true},{"ty":4,"nm":"Stroke 10","sr":1,"st":0,"op":51,"ip":0,"hd":false,"ddd":0,"bm":0,"hasMask":false,"ao":0,"ks":{"a":{"a":0,"k":[0,0,0],"ix":1},"s":{"a":0,"k":[100,100,100],"ix":6},"sk":{"a":0,"k":0},"p":{"a":0,"k":[14.766,-8.203,0],"ix":2},"r":{"a":0,"k":0,"ix":10},"sa":{"a":0,"k":0},"o":{"a":0,"k":100,"ix":11}},"ef":[],"shapes":[{"ty":"gr","bm":0,"hd":false,"mn":"ADBE Vector Group","nm":"Stroke 10","ix":1,"cix":2,"np":2,"it":[{"ty":"sh","bm":0,"hd":false,"mn":"ADBE Vector Shape - Group","nm":"Path 1","ix":1,"d":1,"ks":{"a":0,"k":{"c":false,"i":[[3.03,4.735],[5.15,-3.3050000000000006],[-2.5,-3.3150000000000004]],"o":[[5.15,0.8050000000000002],[0.9300000000000002,-5.575],[-4.62,0.615]],"v":[[3.03,4.735],[3.04,-4.445],[-4.62,0.615]]},"ix":2},"_render":true},{"ty":"st","bm":0,"hd":false,"mn":"ADBE Vector Graphic - Stroke","nm":"Stroke 1","lc":2,"lj":2,"ml":1,"o":{"a":0,"k":100,"ix":4},"w":{"a":0,"k":3,"ix":5},"c":{"a":0,"k":[0.1333,0.7216,0.8118,1],"ix":3},"_render":true},{"ty":"tr","a":{"a":0,"k":[0,0],"ix":1},"s":{"a":0,"k":[100,100],"ix":3},"sk":{"a":0,"k":0,"ix":4},"p":{"a":0,"k":[0,0],"ix":2},"r":{"a":0,"k":0,"ix":6},"sa":{"a":0,"k":0,"ix":5},"o":{"a":0,"k":100,"ix":7},"_render":true}],"_render":true}],"ind":6,"parent":7,"completed":true},{"ty":4,"nm":"Stroke 18","sr":1,"st":0,"op":51,"ip":0,"hd":false,"ddd":0,"bm":0,"hasMask":false,"ao":0,"ks":{"a":{"a":0,"k":[0,0,0],"ix":1},"s":{"a":0,"k":[100,100,100],"ix":6},"sk":{"a":0,"k":0},"p":{"a":1,"k":[{"o":{"x":0.863,"y":0},"i":{"x":0.63,"y":1},"s":[-1.003,-4.038,0],"t":2,"ti":null,"to":null},{"o":{"x":0.423,"y":0},"i":{"x":0.216,"y":1},"s":[-4.64,-4.188,0],"t":14,"ti":null,"to":null},{"o":{"x":0.863,"y":0},"i":{"x":0.63,"y":1},"s":[1.999,-3.34,0],"t":26,"ti":null,"to":null},{"o":{"x":0.323,"y":0},"i":{"x":0.103,"y":1},"s":[-4.64,-4.188,0],"t":38,"ti":null,"to":null},{"s":[-1.003,-4.038,0],"t":50}],"ix":2},"r":{"a":0,"k":0,"ix":10},"sa":{"a":0,"k":0},"o":{"a":0,"k":100,"ix":11}},"ef":[],"shapes":[{"ty":"gr","bm":0,"hd":false,"mn":"ADBE Vector Group","nm":"Stroke 18","ix":1,"cix":2,"np":2,"it":[{"ty":"sh","bm":0,"hd":false,"mn":"ADBE Vector Shape - Group","nm":"Path 1","ix":1,"d":1,"ks":{"a":1,"k":[{"o":{"x":0.45,"y":0},"i":{"x":0.3,"y":1},"s":[{"c":true,"i":[[-13.295,-11.195],[-13.835,4.905],[11.095,11.004999999999999]],"o":[[-17.075,-4.175000000000001],[1.7250000000000005,13.295000000000002],[14.875,3.985]],"v":[[-13.295,-11.195],[-6.055,9.095],[14.875,3.985]]}],"t":2},{"o":{"x":0.45,"y":0},"i":{"x":0.3,"y":1},"s":[{"c":true,"i":[[-8.217,-8.771],[-9.482,-3.8280000000000003],[7.9830000000000005,3.778]],"o":[[-9.432,-6.2570000000000014],[6.078,4.562],[9.65,0.672]],"v":[[-8.217,-8.771],[-1.702,0.362],[9.65,0.672]]}],"t":14},{"o":{"x":0.45,"y":0},"i":{"x":0.3,"y":1},"s":[{"c":true,"i":[[-13.295,-11.195],[-13.835,4.905],[11.095,11.004999999999999]],"o":[[-17.075,-4.175000000000001],[1.7250000000000005,13.295000000000002],[14.875,3.985]],"v":[[-13.295,-11.195],[-6.055,9.095],[14.875,3.985]]}],"t":26},{"o":{"x":0.45,"y":0},"i":{"x":0.3,"y":1},"s":[{"c":true,"i":[[-8.217,-8.771],[-9.482,-3.8280000000000003],[7.9830000000000005,3.778]],"o":[[-9.432,-6.2570000000000014],[6.078,4.562],[9.65,0.672]],"v":[[-8.217,-8.771],[-1.702,0.362],[9.65,0.672]]}],"t":38},{"s":[{"c":true,"i":[[-13.295,-11.195],[-13.835,4.905],[11.095,11.004999999999999]],"o":[[-17.075,-4.175000000000001],[1.7250000000000005,13.295000000000002],[14.875,3.985]],"v":[[-13.295,-11.195],[-6.055,9.095],[14.875,3.985]]}],"t":50}],"ix":2},"_render":true},{"ty":"st","bm":0,"hd":false,"mn":"ADBE Vector Graphic - Stroke","nm":"Stroke 1","lc":2,"lj":2,"ml":1,"o":{"a":0,"k":100,"ix":4},"w":{"a":0,"k":3,"ix":5},"c":{"a":0,"k":[0.1333,0.7216,0.8118,1],"ix":3},"_render":true},{"ty":"tr","a":{"a":0,"k":[0,0],"ix":1},"s":{"a":0,"k":[100,100],"ix":3},"sk":{"a":0,"k":0,"ix":4},"p":{"a":0,"k":[0,0],"ix":2},"r":{"a":0,"k":0,"ix":6},"sa":{"a":0,"k":0,"ix":5},"o":{"a":0,"k":100,"ix":7},"_render":true}],"_render":true}],"ind":7,"parent":8,"completed":true},{"ty":4,"nm":"Stroke 6","sr":1,"st":0,"op":51,"ip":0,"hd":false,"ddd":0,"bm":0,"hasMask":false,"ao":0,"ks":{"a":{"a":0,"k":[-21,25,0],"ix":1},"s":{"a":0,"k":[100,100,100],"ix":6},"sk":{"a":0,"k":0},"p":{"a":1,"k":[{"o":{"x":0.863,"y":0},"i":{"x":0.63,"y":1},"s":[142.613,137.164,0],"t":2,"ti":[5.887,-25.414,0],"to":[0,0,0]},{"o":{"x":0.423,"y":0},"i":{"x":0.216,"y":1},"s":[120.113,182.164,0],"t":14,"ti":[0,0,0],"to":[-11.387,-27.336,0]},{"o":{"x":0.863,"y":0},"i":{"x":0.63,"y":1},"s":[90.613,137.164,0],"t":26,"ti":[-12.863,-28.664,0],"to":[0,0,0]},{"o":{"x":0.323,"y":0},"i":{"x":0.103,"y":1},"s":[120.113,182.164,0],"t":38,"ti":[0,0,0],"to":[-11.387,-27.336,0]},{"s":[142.613,137.164,0],"t":50}],"ix":2},"r":{"a":1,"k":[{"o":{"x":0.863,"y":0},"i":{"x":0.63,"y":1},"s":[0],"t":2},{"o":{"x":0.423,"y":0},"i":{"x":0.216,"y":1},"s":[-24.243],"t":14},{"o":{"x":0.863,"y":0},"i":{"x":0.63,"y":1},"s":[-46.006],"t":26},{"o":{"x":0.323,"y":0},"i":{"x":0.103,"y":1},"s":[-24.243],"t":38},{"s":[0],"t":50}],"ix":10},"sa":{"a":0,"k":0},"o":{"a":0,"k":100,"ix":11}},"ef":[],"shapes":[{"ty":"gr","bm":0,"hd":false,"mn":"ADBE Vector Group","nm":"Stroke 6","ix":1,"cix":2,"np":3,"it":[{"ty":"sh","bm":0,"hd":false,"mn":"ADBE Vector Shape - Group","nm":"Path 1","ix":1,"d":1,"ks":{"a":1,"k":[{"o":{"x":0.863,"y":0},"i":{"x":0.63,"y":1},"s":[{"c":true,"i":[[-6.435,-46.307],[21.195,-71.477],[36.555,-22.437],[67.175,-2.0069999999999997],[28.125,27.033],[17.335,63.553],[-24.475,32.653],[-56.465,38.783],[-47.245,-12.947],[-58.595,-43.897000000000006]],"o":[[-6.435,-46.307],[42.625,-57.857],[36.555,-22.437],[59.655,17.863],[28.125,27.033],[-1.5549999999999997,67.923],[-24.475,32.653],[-68.795,15.963000000000001],[-47.245,-12.947],[-41.915000000000006,-62.297]],"v":[[-6.435,-46.307],[31.905,-64.667],[36.555,-22.437],[63.415,7.933],[28.125,27.033],[7.885,65.743],[-24.475,32.653],[-62.625,27.373],[-47.245,-12.947],[-50.255,-53.097]]}],"t":2},{"o":{"x":0.423,"y":0},"i":{"x":0.216,"y":1},"s":[{"c":true,"i":[[-6.972,-35.528],[15.628,-52.635],[29.237,-13.456],[54.214000000000006,6.513],[16.416,27.136],[0.702,55.217],[-23.08,30.133],[-47.183,37.384],[-40.403,-5.2],[-48.916000000000004,-33.69800000000001]],"o":[[-6.972,-35.528],[36.35,-37.959999999999994],[29.237,-13.456],[45.702000000000005,25.979],[16.416,27.136],[-14.356,52.306],[-23.08,30.133],[-57.123000000000005,19.584000000000003],[-40.403,-5.2],[-31.332,-51.238]],"v":[[-6.972,-35.528],[25.986,-45.3],[29.237,-13.456],[49.956,16.25],[16.416,27.136],[-6.959,53.736],[-23.08,30.133],[-52.152,28.486],[-40.403,-5.2],[-40.124,-42.468]]}],"t":14},{"o":{"x":0.863,"y":0},"i":{"x":0.63,"y":1},"s":[{"c":true,"i":[[-6.435,-46.307],[21.195,-71.477],[36.555,-22.437],[67.175,-2.0069999999999997],[28.125,27.033],[17.335,63.553],[-24.475,32.653],[-56.465,38.783],[-47.245,-12.947],[-58.595,-43.897000000000006]],"o":[[-6.435,-46.307],[42.625,-57.857],[36.555,-22.437],[59.655,17.863],[28.125,27.033],[-1.5549999999999997,67.923],[-24.475,32.653],[-68.795,15.963000000000001],[-47.245,-12.947],[-41.915000000000006,-62.297]],"v":[[-6.435,-46.307],[31.905,-64.667],[36.555,-22.437],[63.415,7.933],[28.125,27.033],[7.885,65.743],[-24.475,32.653],[-62.625,27.373],[-47.245,-12.947],[-50.255,-53.097]]}],"t":26},{"o":{"x":0.323,"y":0},"i":{"x":0.103,"y":1},"s":[{"c":true,"i":[[-8.434,-40.964],[18.432,-59.049],[33.3,-16.547],[55.962,2.365],[16.328,24.766],[0.702,55.217],[-23.08,30.133],[-49.435,36.296],[-42.014,-4.058],[-50.74,-34.518]],"o":[[-8.434,-40.964],[39.153999999999996,-44.373999999999995],[33.3,-16.547],[47.45,21.831],[16.328,24.766],[-14.356,52.306],[-23.08,30.133],[-59.375,18.496000000000002],[-42.014,-4.058],[-33.156,-52.05799999999999]],"v":[[-8.434,-40.964],[28.79,-51.714],[33.3,-16.547],[51.704,12.102],[16.328,24.766],[-6.959,53.736],[-23.08,30.133],[-54.404,27.398],[-42.014,-4.058],[-41.948,-43.288]]}],"t":38},{"s":[{"c":true,"i":[[-6.435,-46.307],[21.195,-71.477],[36.555,-22.437],[67.175,-2.0069999999999997],[28.125,27.033],[17.335,63.553],[-24.475,32.653],[-56.465,38.783],[-47.245,-12.947],[-58.595,-43.897000000000006]],"o":[[-6.435,-46.307],[42.625,-57.857],[36.555,-22.437],[59.655,17.863],[28.125,27.033],[-1.5549999999999997,67.923],[-24.475,32.653],[-68.795,15.963000000000001],[-47.245,-12.947],[-41.915000000000006,-62.297]],"v":[[-6.435,-46.307],[31.905,-64.667],[36.555,-22.437],[63.415,7.933],[28.125,27.033],[7.885,65.743],[-24.475,32.653],[-62.625,27.373],[-47.245,-12.947],[-50.255,-53.097]]}],"t":50}],"ix":2},"_render":true},{"ty":"st","bm":0,"hd":false,"mn":"ADBE Vector Graphic - Stroke","nm":"Stroke 1","lc":2,"lj":2,"ml":1,"o":{"a":0,"k":100,"ix":4},"w":{"a":0,"k":3,"ix":5},"c":{"a":0,"k":[0.1333,0.7216,0.8118,1],"ix":3},"_render":true},{"ty":"fl","bm":0,"hd":false,"mn":"ADBE Vector Graphic - Fill","nm":"Fill 1","c":{"a":0,"k":[0.4,0.851,0.9098,1],"ix":4},"r":1,"o":{"a":0,"k":100,"ix":5},"_render":true},{"ty":"tr","a":{"a":0,"k":[0,0],"ix":1},"s":{"a":0,"k":[100,100],"ix":3},"sk":{"a":0,"k":0,"ix":4},"p":{"a":0,"k":[0,0],"ix":2},"r":{"a":0,"k":0,"ix":6},"sa":{"a":0,"k":0,"ix":5},"o":{"a":0,"k":100,"ix":7},"_render":true}],"_render":true}],"ind":8,"completed":true},{"ty":4,"nm":"Stroke 46 :M 4","sr":1,"st":38,"op":51,"ip":38,"hd":false,"ddd":0,"bm":0,"hasMask":false,"ao":0,"ks":{"a":{"a":0,"k":[126.398,177.396,0],"ix":1},"s":{"a":0,"k":[100,100,100],"ix":6},"sk":{"a":0,"k":0},"p":{"a":0,"k":[126.398,177.396,0],"ix":2},"r":{"a":0,"k":0,"ix":10},"sa":{"a":0,"k":0},"o":{"a":0,"k":100,"ix":11}},"ef":[],"shapes":[{"ty":"gr","bm":0,"hd":false,"mn":"ADBE Vector Group","nm":"Stroke 446","ix":1,"cix":2,"np":1,"it":[{"ty":"gr","bm":0,"hd":false,"mn":"ADBE Vector Group","nm":"Stroke 46","ix":1,"cix":2,"np":2,"it":[{"ty":"sh","bm":0,"hd":false,"mn":"ADBE Vector Shape - Group","nm":"Path 1","ix":1,"d":1,"ks":{"a":0,"k":{"c":false,"i":[[-3.422,6.902],[1.5180000000000002,-3.6979999999999995]],"o":[[-1.1320000000000001,1.3719999999999999],[3.418,-6.898]],"v":[[-3.422,6.902],[3.418,-6.898]]},"ix":2},"_render":true},{"ty":"st","bm":0,"hd":false,"mn":"ADBE Vector Graphic - Stroke","nm":"Stroke 1","lc":2,"lj":2,"ml":1,"o":{"a":0,"k":100,"ix":4},"w":{"a":0,"k":3,"ix":5},"c":{"a":0,"k":[0.035,0.4077,0.465,1],"ix":3},"_render":true},{"ty":"tr","a":{"a":0,"k":[0,0],"ix":1},"s":{"a":0,"k":[100,100],"ix":3},"sk":{"a":0,"k":0,"ix":4},"p":{"a":0,"k":[0,0],"ix":2},"r":{"a":0,"k":0,"ix":6},"sa":{"a":0,"k":0,"ix":5},"o":{"a":0,"k":100,"ix":7},"_render":true}],"_render":true},{"ty":"tr","a":{"a":0,"k":[0,0],"ix":1},"s":{"a":0,"k":[100,100],"ix":3},"sk":{"a":0,"k":0,"ix":4},"p":{"a":0,"k":[132.731,179.741],"ix":2},"r":{"a":0,"k":0,"ix":6},"sa":{"a":0,"k":0,"ix":5},"o":{"a":0,"k":100,"ix":7},"_render":true}],"_render":true},{"ty":"gr","bm":0,"hd":false,"mn":"ADBE Vector Group","nm":"Stroke 442","ix":2,"cix":2,"np":1,"it":[{"ty":"gr","bm":0,"hd":false,"mn":"ADBE Vector Group","nm":"Stroke 42","ix":1,"cix":2,"np":2,"it":[{"ty":"sh","bm":0,"hd":false,"mn":"ADBE Vector Shape - Group","nm":"Path 1","ix":1,"d":1,"ks":{"a":0,"k":{"c":false,"i":[[-8.793,21.925],[1.9170000000000007,-10.845]],"o":[[-4.812999999999999,5.015000000000001],[8.797,-21.925]],"v":[[-8.793,21.925],[8.797,-21.925]]},"ix":2},"_render":true},{"ty":"st","bm":0,"hd":false,"mn":"ADBE Vector Graphic - Stroke","nm":"Stroke 1","lc":2,"lj":2,"ml":1,"o":{"a":0,"k":100,"ix":4},"w":{"a":0,"k":3,"ix":5},"c":{"a":0,"k":[0.035,0.4077,0.465,1],"ix":3},"_render":true},{"ty":"tr","a":{"a":0,"k":[0,0],"ix":1},"s":{"a":0,"k":[100,100],"ix":3},"sk":{"a":0,"k":0,"ix":4},"p":{"a":0,"k":[0,0],"ix":2},"r":{"a":0,"k":0,"ix":6},"sa":{"a":0,"k":0,"ix":5},"o":{"a":0,"k":100,"ix":7},"_render":true}],"_render":true},{"ty":"tr","a":{"a":0,"k":[0,0],"ix":1},"s":{"a":0,"k":[100,100],"ix":3},"sk":{"a":0,"k":0,"ix":4},"p":{"a":0,"k":[125.441,177.396],"ix":2},"r":{"a":0,"k":0,"ix":6},"sa":{"a":0,"k":0,"ix":5},"o":{"a":0,"k":100,"ix":7},"_render":true}],"_render":true},{"ty":"tm","bm":0,"hd":false,"mn":"ADBE Vector Filter - Trim","nm":"Trim Paths 1","ix":3,"e":{"a":1,"k":[{"o":{"x":0.45,"y":0},"i":{"x":0.3,"y":1},"s":[0],"t":38},{"s":[100],"t":50}],"ix":2},"o":{"a":0,"k":0,"ix":3},"s":{"a":0,"k":0,"ix":1},"m":1,"_render":true}],"ind":9,"completed":true},{"ty":4,"nm":"Stroke 46 :M 3","sr":1,"st":0,"op":38,"ip":26,"hd":false,"ddd":0,"bm":0,"hasMask":false,"ao":0,"ks":{"a":{"a":0,"k":[126.398,177.396,0],"ix":1},"s":{"a":0,"k":[-100,100,100],"ix":6},"sk":{"a":0,"k":0},"p":{"a":0,"k":[99.398,177.396,0],"ix":2},"r":{"a":0,"k":0,"ix":10},"sa":{"a":0,"k":0},"o":{"a":0,"k":100,"ix":11}},"ef":[],"shapes":[{"ty":"gr","bm":0,"hd":false,"mn":"ADBE Vector Group","nm":"Stroke 446","ix":1,"cix":2,"np":1,"it":[{"ty":"gr","bm":0,"hd":false,"mn":"ADBE Vector Group","nm":"Stroke 46","ix":1,"cix":2,"np":2,"it":[{"ty":"sh","bm":0,"hd":false,"mn":"ADBE Vector Shape - Group","nm":"Path 1","ix":1,"d":1,"ks":{"a":0,"k":{"c":false,"i":[[3.418,-6.898],[-1.1320000000000001,1.3719999999999999]],"o":[[1.5180000000000002,-3.6979999999999995],[-3.422,6.902]],"v":[[3.418,-6.898],[-3.422,6.902]]},"ix":2},"_render":true},{"ty":"st","bm":0,"hd":false,"mn":"ADBE Vector Graphic - Stroke","nm":"Stroke 1","lc":2,"lj":2,"ml":1,"o":{"a":0,"k":100,"ix":4},"w":{"a":0,"k":3,"ix":5},"c":{"a":0,"k":[0.035,0.4077,0.465,1],"ix":3},"_render":true},{"ty":"tr","a":{"a":0,"k":[0,0],"ix":1},"s":{"a":0,"k":[100,100],"ix":3},"sk":{"a":0,"k":0,"ix":4},"p":{"a":0,"k":[0,0],"ix":2},"r":{"a":0,"k":0,"ix":6},"sa":{"a":0,"k":0,"ix":5},"o":{"a":0,"k":100,"ix":7},"_render":true}],"_render":true},{"ty":"tr","a":{"a":0,"k":[0,0],"ix":1},"s":{"a":0,"k":[100,100],"ix":3},"sk":{"a":0,"k":0,"ix":4},"p":{"a":0,"k":[132.731,179.741],"ix":2},"r":{"a":0,"k":0,"ix":6},"sa":{"a":0,"k":0,"ix":5},"o":{"a":0,"k":100,"ix":7},"_render":true}],"_render":true},{"ty":"gr","bm":0,"hd":false,"mn":"ADBE Vector Group","nm":"Stroke 442","ix":2,"cix":2,"np":1,"it":[{"ty":"gr","bm":0,"hd":false,"mn":"ADBE Vector Group","nm":"Stroke 42","ix":1,"cix":2,"np":2,"it":[{"ty":"sh","bm":0,"hd":false,"mn":"ADBE Vector Shape - Group","nm":"Path 1","ix":1,"d":1,"ks":{"a":0,"k":{"c":false,"i":[[8.797,-21.925],[-4.812999999999999,5.015000000000001]],"o":[[1.9170000000000007,-10.845],[-8.793,21.925]],"v":[[8.797,-21.925],[-8.793,21.925]]},"ix":2},"_render":true},{"ty":"st","bm":0,"hd":false,"mn":"ADBE Vector Graphic - Stroke","nm":"Stroke 1","lc":2,"lj":2,"ml":1,"o":{"a":0,"k":100,"ix":4},"w":{"a":0,"k":3,"ix":5},"c":{"a":0,"k":[0.035,0.4077,0.465,1],"ix":3},"_render":true},{"ty":"tr","a":{"a":0,"k":[0,0],"ix":1},"s":{"a":0,"k":[100,100],"ix":3},"sk":{"a":0,"k":0,"ix":4},"p":{"a":0,"k":[0,0],"ix":2},"r":{"a":0,"k":0,"ix":6},"sa":{"a":0,"k":0,"ix":5},"o":{"a":0,"k":100,"ix":7},"_render":true}],"_render":true},{"ty":"tr","a":{"a":0,"k":[0,0],"ix":1},"s":{"a":0,"k":[100,100],"ix":3},"sk":{"a":0,"k":0,"ix":4},"p":{"a":0,"k":[125.441,177.396],"ix":2},"r":{"a":0,"k":0,"ix":6},"sa":{"a":0,"k":0,"ix":5},"o":{"a":0,"k":100,"ix":7},"_render":true}],"_render":true},{"ty":"tm","bm":0,"hd":false,"mn":"ADBE Vector Filter - Trim","nm":"Trim Paths 1","ix":3,"e":{"a":1,"k":[{"o":{"x":0.45,"y":0},"i":{"x":0.3,"y":1},"s":[0],"t":26},{"s":[100],"t":38}],"ix":2},"o":{"a":0,"k":0,"ix":3},"s":{"a":0,"k":100,"ix":1},"m":1,"_render":true}],"ind":10,"completed":true},{"ty":4,"nm":"Stroke 46 :M 2","sr":1,"st":0,"op":26,"ip":14,"hd":false,"ddd":0,"bm":0,"hasMask":false,"ao":0,"ks":{"a":{"a":0,"k":[126.398,177.396,0],"ix":1},"s":{"a":0,"k":[-100,100,100],"ix":6},"sk":{"a":0,"k":0},"p":{"a":0,"k":[99.398,177.396,0],"ix":2},"r":{"a":0,"k":0,"ix":10},"sa":{"a":0,"k":0},"o":{"a":0,"k":100,"ix":11}},"ef":[],"shapes":[{"ty":"gr","bm":0,"hd":false,"mn":"ADBE Vector Group","nm":"Stroke 446","ix":1,"cix":2,"np":1,"it":[{"ty":"gr","bm":0,"hd":false,"mn":"ADBE Vector Group","nm":"Stroke 46","ix":1,"cix":2,"np":2,"it":[{"ty":"sh","bm":0,"hd":false,"mn":"ADBE Vector Shape - Group","nm":"Path 1","ix":1,"d":1,"ks":{"a":0,"k":{"c":false,"i":[[-3.422,6.902],[1.5180000000000002,-3.6979999999999995]],"o":[[-1.1320000000000001,1.3719999999999999],[3.418,-6.898]],"v":[[-3.422,6.902],[3.418,-6.898]]},"ix":2},"_render":true},{"ty":"st","bm":0,"hd":false,"mn":"ADBE Vector Graphic - Stroke","nm":"Stroke 1","lc":2,"lj":2,"ml":1,"o":{"a":0,"k":100,"ix":4},"w":{"a":0,"k":3,"ix":5},"c":{"a":0,"k":[0.035,0.4077,0.465,1],"ix":3},"_render":true},{"ty":"tr","a":{"a":0,"k":[0,0],"ix":1},"s":{"a":0,"k":[100,100],"ix":3},"sk":{"a":0,"k":0,"ix":4},"p":{"a":0,"k":[0,0],"ix":2},"r":{"a":0,"k":0,"ix":6},"sa":{"a":0,"k":0,"ix":5},"o":{"a":0,"k":100,"ix":7},"_render":true}],"_render":true},{"ty":"tr","a":{"a":0,"k":[0,0],"ix":1},"s":{"a":0,"k":[100,100],"ix":3},"sk":{"a":0,"k":0,"ix":4},"p":{"a":0,"k":[132.731,179.741],"ix":2},"r":{"a":0,"k":0,"ix":6},"sa":{"a":0,"k":0,"ix":5},"o":{"a":0,"k":100,"ix":7},"_render":true}],"_render":true},{"ty":"gr","bm":0,"hd":false,"mn":"ADBE Vector Group","nm":"Stroke 442","ix":2,"cix":2,"np":1,"it":[{"ty":"gr","bm":0,"hd":false,"mn":"ADBE Vector Group","nm":"Stroke 42","ix":1,"cix":2,"np":2,"it":[{"ty":"sh","bm":0,"hd":false,"mn":"ADBE Vector Shape - Group","nm":"Path 1","ix":1,"d":1,"ks":{"a":0,"k":{"c":false,"i":[[-8.793,21.925],[1.9170000000000007,-10.845]],"o":[[-4.812999999999999,5.015000000000001],[8.797,-21.925]],"v":[[-8.793,21.925],[8.797,-21.925]]},"ix":2},"_render":true},{"ty":"st","bm":0,"hd":false,"mn":"ADBE Vector Graphic - Stroke","nm":"Stroke 1","lc":2,"lj":2,"ml":1,"o":{"a":0,"k":100,"ix":4},"w":{"a":0,"k":3,"ix":5},"c":{"a":0,"k":[0.035,0.4077,0.465,1],"ix":3},"_render":true},{"ty":"tr","a":{"a":0,"k":[0,0],"ix":1},"s":{"a":0,"k":[100,100],"ix":3},"sk":{"a":0,"k":0,"ix":4},"p":{"a":0,"k":[0,0],"ix":2},"r":{"a":0,"k":0,"ix":6},"sa":{"a":0,"k":0,"ix":5},"o":{"a":0,"k":100,"ix":7},"_render":true}],"_render":true},{"ty":"tr","a":{"a":0,"k":[0,0],"ix":1},"s":{"a":0,"k":[100,100],"ix":3},"sk":{"a":0,"k":0,"ix":4},"p":{"a":0,"k":[125.441,177.396],"ix":2},"r":{"a":0,"k":0,"ix":6},"sa":{"a":0,"k":0,"ix":5},"o":{"a":0,"k":100,"ix":7},"_render":true}],"_render":true},{"ty":"tm","bm":0,"hd":false,"mn":"ADBE Vector Filter - Trim","nm":"Trim Paths 1","ix":3,"e":{"a":1,"k":[{"o":{"x":0.45,"y":0},"i":{"x":0.3,"y":1},"s":[0],"t":14},{"s":[100],"t":26}],"ix":2},"o":{"a":0,"k":0,"ix":3},"s":{"a":0,"k":0,"ix":1},"m":1,"_render":true}],"ind":11,"completed":true},{"ty":4,"nm":"Stroke 46 :M","sr":1,"st":0,"op":14,"ip":0,"hd":false,"ddd":0,"bm":0,"hasMask":false,"ao":0,"ks":{"a":{"a":0,"k":[126.398,177.396,0],"ix":1},"s":{"a":0,"k":[100,100,100],"ix":6},"sk":{"a":0,"k":0},"p":{"a":0,"k":[126.398,177.396,0],"ix":2},"r":{"a":0,"k":0,"ix":10},"sa":{"a":0,"k":0},"o":{"a":0,"k":100,"ix":11}},"ef":[],"shapes":[{"ty":"gr","bm":0,"hd":false,"mn":"ADBE Vector Group","nm":"Stroke 446","ix":1,"cix":2,"np":1,"it":[{"ty":"gr","bm":0,"hd":false,"mn":"ADBE Vector Group","nm":"Stroke 46","ix":1,"cix":2,"np":2,"it":[{"ty":"sh","bm":0,"hd":false,"mn":"ADBE Vector Shape - Group","nm":"Path 1","ix":1,"d":1,"ks":{"a":0,"k":{"c":false,"i":[[3.418,-6.898],[-1.1320000000000001,1.3719999999999999]],"o":[[1.5180000000000002,-3.6979999999999995],[-3.422,6.902]],"v":[[3.418,-6.898],[-3.422,6.902]]},"ix":2},"_render":true},{"ty":"st","bm":0,"hd":false,"mn":"ADBE Vector Graphic - Stroke","nm":"Stroke 1","lc":2,"lj":2,"ml":1,"o":{"a":0,"k":100,"ix":4},"w":{"a":0,"k":3,"ix":5},"c":{"a":0,"k":[0.035,0.4077,0.465,1],"ix":3},"_render":true},{"ty":"tr","a":{"a":0,"k":[0,0],"ix":1},"s":{"a":0,"k":[100,100],"ix":3},"sk":{"a":0,"k":0,"ix":4},"p":{"a":0,"k":[0,0],"ix":2},"r":{"a":0,"k":0,"ix":6},"sa":{"a":0,"k":0,"ix":5},"o":{"a":0,"k":100,"ix":7},"_render":true}],"_render":true},{"ty":"tr","a":{"a":0,"k":[0,0],"ix":1},"s":{"a":0,"k":[100,100],"ix":3},"sk":{"a":0,"k":0,"ix":4},"p":{"a":0,"k":[132.731,179.741],"ix":2},"r":{"a":0,"k":0,"ix":6},"sa":{"a":0,"k":0,"ix":5},"o":{"a":0,"k":100,"ix":7},"_render":true}],"_render":true},{"ty":"gr","bm":0,"hd":false,"mn":"ADBE Vector Group","nm":"Stroke 442","ix":2,"cix":2,"np":1,"it":[{"ty":"gr","bm":0,"hd":false,"mn":"ADBE Vector Group","nm":"Stroke 42","ix":1,"cix":2,"np":2,"it":[{"ty":"sh","bm":0,"hd":false,"mn":"ADBE Vector Shape - Group","nm":"Path 1","ix":1,"d":1,"ks":{"a":0,"k":{"c":false,"i":[[8.797,-21.925],[-4.812999999999999,5.015000000000001]],"o":[[1.9170000000000007,-10.845],[-8.793,21.925]],"v":[[8.797,-21.925],[-8.793,21.925]]},"ix":2},"_render":true},{"ty":"st","bm":0,"hd":false,"mn":"ADBE Vector Graphic - Stroke","nm":"Stroke 1","lc":2,"lj":2,"ml":1,"o":{"a":0,"k":100,"ix":4},"w":{"a":0,"k":3,"ix":5},"c":{"a":0,"k":[0.035,0.4077,0.465,1],"ix":3},"_render":true},{"ty":"tr","a":{"a":0,"k":[0,0],"ix":1},"s":{"a":0,"k":[100,100],"ix":3},"sk":{"a":0,"k":0,"ix":4},"p":{"a":0,"k":[0,0],"ix":2},"r":{"a":0,"k":0,"ix":6},"sa":{"a":0,"k":0,"ix":5},"o":{"a":0,"k":100,"ix":7},"_render":true}],"_render":true},{"ty":"tr","a":{"a":0,"k":[0,0],"ix":1},"s":{"a":0,"k":[100,100],"ix":3},"sk":{"a":0,"k":0,"ix":4},"p":{"a":0,"k":[125.441,177.396],"ix":2},"r":{"a":0,"k":0,"ix":6},"sa":{"a":0,"k":0,"ix":5},"o":{"a":0,"k":100,"ix":7},"_render":true}],"_render":true},{"ty":"tm","bm":0,"hd":false,"mn":"ADBE Vector Filter - Trim","nm":"Trim Paths 1","ix":3,"e":{"a":0,"k":100,"ix":2},"o":{"a":0,"k":0,"ix":3},"s":{"a":1,"k":[{"o":{"x":0.45,"y":0},"i":{"x":0.3,"y":1},"s":[0],"t":2},{"s":[100],"t":14}],"ix":1},"m":1,"_render":true}],"ind":12,"completed":true},{"ty":4,"nm":"Stroke 48","sr":1,"st":36,"op":51,"ip":36,"hd":false,"ddd":0,"bm":0,"hasMask":false,"ao":0,"ks":{"a":{"a":0,"k":[-7.59,-7.833,0],"ix":1},"s":{"a":0,"k":[100,100,100],"ix":6},"sk":{"a":0,"k":0},"p":{"a":0,"k":[84.286,188.323,0],"ix":2},"r":{"a":0,"k":0,"ix":10},"sa":{"a":0,"k":0},"o":{"a":0,"k":100,"ix":11}},"ef":[],"shapes":[{"ty":"gr","bm":0,"hd":false,"mn":"ADBE Vector Group","nm":"Stroke 38","ix":1,"cix":2,"np":3,"it":[{"ty":"sh","bm":0,"hd":false,"mn":"ADBE Vector Shape - Group","nm":"Path 1","ix":1,"d":1,"ks":{"a":0,"k":{"c":false,"i":[[7.59,7.827],[-3.5599999999999996,-5.793]],"o":[[4.33,2.327],[-7.59,-7.833]],"v":[[7.59,7.837],[-7.59,-7.833]]},"ix":2},"_render":true},{"ty":"st","bm":0,"hd":false,"mn":"ADBE Vector Graphic - Stroke","nm":"Stroke 1","lc":2,"lj":2,"ml":1,"o":{"a":0,"k":100,"ix":4},"w":{"a":0,"k":3,"ix":5},"c":{"a":0,"k":[0.035,0.4077,0.465,1],"ix":3},"_render":true},{"ty":"tm","bm":0,"hd":false,"mn":"ADBE Vector Filter - Trim","nm":"Trim Paths 1","ix":3,"e":{"a":0,"k":100,"ix":2},"o":{"a":0,"k":0,"ix":3},"s":{"a":0,"k":0,"ix":1},"m":1,"_render":true},{"ty":"tr","a":{"a":0,"k":[0,0],"ix":1},"s":{"a":0,"k":[100,100],"ix":3},"sk":{"a":0,"k":0,"ix":4},"p":{"a":0,"k":[0,0],"ix":2},"r":{"a":0,"k":0,"ix":6},"sa":{"a":0,"k":0,"ix":5},"o":{"a":0,"k":100,"ix":7},"_render":true}],"_render":true},{"ty":"tm","bm":0,"hd":false,"mn":"ADBE Vector Filter - Trim","nm":"Trim Paths 1","ix":2,"e":{"a":1,"k":[{"o":{"x":0.45,"y":0},"i":{"x":0.3,"y":1},"s":[0],"t":36},{"s":[100],"t":48}],"ix":2},"o":{"a":0,"k":0,"ix":3},"s":{"a":0,"k":0,"ix":1},"m":1,"_render":true}],"ind":13,"completed":true},{"ty":4,"nm":"Stroke 47","sr":1,"st":0,"op":36,"ip":24,"hd":false,"ddd":0,"bm":0,"hasMask":false,"ao":0,"ks":{"a":{"a":0,"k":[4.41,7.911,0],"ix":1},"s":{"a":0,"k":[100,100,100],"ix":6},"sk":{"a":0,"k":0},"p":{"a":0,"k":[146.036,204.066,0],"ix":2},"r":{"a":0,"k":0,"ix":10},"sa":{"a":0,"k":0},"o":{"a":0,"k":100,"ix":11}},"ef":[],"shapes":[{"ty":"gr","bm":0,"hd":false,"mn":"ADBE Vector Group","nm":"Stroke 39","ix":1,"cix":2,"np":3,"it":[{"ty":"sh","bm":0,"hd":false,"mn":"ADBE Vector Shape - Group","nm":"Path 1","ix":1,"d":1,"ks":{"a":0,"k":{"c":false,"i":[[-19.59,-7.759],[-7.67,2.401]],"o":[[-15.559999999999999,-5.719],[-4.41,7.901]],"v":[[-19.59,-7.759],[-4.41,7.911]]},"ix":2},"_render":true},{"ty":"st","bm":0,"hd":false,"mn":"ADBE Vector Graphic - Stroke","nm":"Stroke 1","lc":2,"lj":2,"ml":1,"o":{"a":0,"k":100,"ix":4},"w":{"a":0,"k":3,"ix":5},"c":{"a":0,"k":[0.035,0.4077,0.465,1],"ix":3},"_render":true},{"ty":"tm","bm":0,"hd":false,"mn":"ADBE Vector Filter - Trim","nm":"Trim Paths 1","ix":3,"e":{"a":0,"k":100,"ix":2},"o":{"a":0,"k":0,"ix":3},"s":{"a":0,"k":0,"ix":1},"m":1,"_render":true},{"ty":"tr","a":{"a":0,"k":[0,0],"ix":1},"s":{"a":0,"k":[-100,100],"ix":3},"sk":{"a":0,"k":0,"ix":4},"p":{"a":0,"k":[0,0],"ix":2},"r":{"a":0,"k":0,"ix":6},"sa":{"a":0,"k":0,"ix":5},"o":{"a":0,"k":100,"ix":7},"_render":true}],"_render":true},{"ty":"tm","bm":0,"hd":false,"mn":"ADBE Vector Filter - Trim","nm":"Trim Paths 1","ix":2,"e":{"a":0,"k":100,"ix":2},"o":{"a":0,"k":0,"ix":3},"s":{"a":1,"k":[{"o":{"x":0.45,"y":0},"i":{"x":0.3,"y":1},"s":[0],"t":24},{"s":[100],"t":36}],"ix":1},"m":1,"_render":true}],"ind":14,"completed":true},{"ty":4,"nm":"Stroke 39","sr":1,"st":0,"op":24,"ip":12,"hd":false,"ddd":0,"bm":0,"hasMask":false,"ao":0,"ks":{"a":{"a":0,"k":[4.41,7.911,0],"ix":1},"s":{"a":0,"k":[100,100,100],"ix":6},"sk":{"a":0,"k":0},"p":{"a":0,"k":[146.036,204.066,0],"ix":2},"r":{"a":0,"k":0,"ix":10},"sa":{"a":0,"k":0},"o":{"a":0,"k":100,"ix":11}},"ef":[],"shapes":[{"ty":"gr","bm":0,"hd":false,"mn":"ADBE Vector Group","nm":"Stroke 39","ix":1,"cix":2,"np":3,"it":[{"ty":"sh","bm":0,"hd":false,"mn":"ADBE Vector Shape - Group","nm":"Path 1","ix":1,"d":1,"ks":{"a":0,"k":{"c":false,"i":[[-4.41,7.901],[-15.559999999999999,-5.719]],"o":[[-7.67,2.401],[-19.59,-7.759]],"v":[[-4.41,7.911],[-19.59,-7.759]]},"ix":2},"_render":true},{"ty":"st","bm":0,"hd":false,"mn":"ADBE Vector Graphic - Stroke","nm":"Stroke 1","lc":2,"lj":2,"ml":1,"o":{"a":0,"k":100,"ix":4},"w":{"a":0,"k":3,"ix":5},"c":{"a":0,"k":[0.035,0.4077,0.465,1],"ix":3},"_render":true},{"ty":"tm","bm":0,"hd":false,"mn":"ADBE Vector Filter - Trim","nm":"Trim Paths 1","ix":3,"e":{"a":1,"k":[{"o":{"x":0.45,"y":0},"i":{"x":0.3,"y":1},"s":[0],"t":12},{"s":[100],"t":24}],"ix":2},"o":{"a":0,"k":0,"ix":3},"s":{"a":0,"k":0,"ix":1},"m":1,"_render":true},{"ty":"tr","a":{"a":0,"k":[0,0],"ix":1},"s":{"a":0,"k":[-100,100],"ix":3},"sk":{"a":0,"k":0,"ix":4},"p":{"a":0,"k":[0,0],"ix":2},"r":{"a":0,"k":0,"ix":6},"sa":{"a":0,"k":0,"ix":5},"o":{"a":0,"k":100,"ix":7},"_render":true}],"_render":true}],"ind":15,"completed":true},{"ty":4,"nm":"Stroke 38","sr":1,"st":0,"op":12,"ip":0,"hd":false,"ddd":0,"bm":0,"hasMask":false,"ao":0,"ks":{"a":{"a":0,"k":[-7.59,-7.833,0],"ix":1},"s":{"a":0,"k":[100,100,100],"ix":6},"sk":{"a":0,"k":0},"p":{"a":0,"k":[84.286,188.323,0],"ix":2},"r":{"a":0,"k":0,"ix":10},"sa":{"a":0,"k":0},"o":{"a":0,"k":100,"ix":11}},"ef":[],"shapes":[{"ty":"gr","bm":0,"hd":false,"mn":"ADBE Vector Group","nm":"Stroke 38","ix":1,"cix":2,"np":3,"it":[{"ty":"sh","bm":0,"hd":false,"mn":"ADBE Vector Shape - Group","nm":"Path 1","ix":1,"d":1,"ks":{"a":0,"k":{"c":false,"i":[[-7.59,-7.833],[4.33,2.327]],"o":[[-3.5599999999999996,-5.793],[7.59,7.827]],"v":[[-7.59,-7.833],[7.59,7.837]]},"ix":2},"_render":true},{"ty":"st","bm":0,"hd":false,"mn":"ADBE Vector Graphic - Stroke","nm":"Stroke 1","lc":2,"lj":2,"ml":1,"o":{"a":0,"k":100,"ix":4},"w":{"a":0,"k":3,"ix":5},"c":{"a":0,"k":[0.035,0.4077,0.465,1],"ix":3},"_render":true},{"ty":"tm","bm":0,"hd":false,"mn":"ADBE Vector Filter - Trim","nm":"Trim Paths 1","ix":3,"e":{"a":0,"k":100,"ix":2},"o":{"a":0,"k":0,"ix":3},"s":{"a":1,"k":[{"o":{"x":0.45,"y":0},"i":{"x":0.3,"y":1},"s":[0],"t":0},{"s":[100],"t":12}],"ix":1},"m":1,"_render":true},{"ty":"tr","a":{"a":0,"k":[0,0],"ix":1},"s":{"a":0,"k":[100,100],"ix":3},"sk":{"a":0,"k":0,"ix":4},"p":{"a":0,"k":[0,0],"ix":2},"r":{"a":0,"k":0,"ix":6},"sa":{"a":0,"k":0,"ix":5},"o":{"a":0,"k":100,"ix":7},"_render":true}],"_render":true}],"ind":16,"completed":true}],"v":"5.7.6","fr":30,"op":51,"ip":0,"assets":[],"__complete":true}